certbot_dns_standalone/__init__.py
certbot_dns_standalone/dns_standalone.py
certbot_dns_standalone/dns_standalone_test.py
certbot_dns_standalone-1.2.1.dist-info/LICENSE.txt
certbot_dns_standalone-1.2.1.dist-info/METADATA
certbot_dns_standalone-1.2.1.dist-info/WHEEL
certbot_dns_standalone-1.2.1.dist-info/entry_points.txt
certbot_dns_standalone-1.2.1.dist-info/top_level.txt
certbot_dns_standalone-1.2.1.dist-info/RECORD
