Metadata-Version: 2.2
Name: certbot-dns-standalone
Version: 1.2.1
Summary: Standalone DNS Authenticator plugin for Certbot
Home-page: https://github.com/siilike/certbot-dns-standalone
Author: Lauri Keel
License: Apache License 2.0
Classifier: Development Status :: 5 - Production/Stable
Classifier: Environment :: Plugins
Classifier: Intended Audience :: System Administrators
Classifier: License :: OSI Approved :: Apache Software License
Classifier: Operating System :: POSIX :: Linux
Classifier: Programming Language :: Python
Classifier: Programming Language :: Python :: 3
Classifier: Programming Language :: Python :: 3.9
Classifier: Programming Language :: Python :: 3.10
Classifier: Programming Language :: Python :: 3.11
Classifier: Programming Language :: Python :: 3.12
Classifier: Topic :: Internet :: WWW/HTTP
Classifier: Topic :: Security
Classifier: Topic :: System :: Installation/Setup
Classifier: Topic :: System :: Networking
Classifier: Topic :: System :: Systems Administration
Classifier: Topic :: Utilities
Requires-Python: >=3.9
License-File: LICENSE.txt
Requires-Dist: acme>=0.21.1
Requires-Dist: certbot>=3.0.0
Requires-Dist: dnslib>=0.9.0
Requires-Dist: mock
Requires-Dist: setuptools
Provides-Extra: docs
Requires-Dist: Sphinx>=1.0; extra == "docs"
Requires-Dist: sphinx_rtd_theme; extra == "docs"
Dynamic: author
Dynamic: classifier
Dynamic: description
Dynamic: description-content-type
Dynamic: home-page
Dynamic: license
Dynamic: provides-extra
Dynamic: requires-dist
Dynamic: requires-python
Dynamic: summary
